[
  {
    "name": "deactivated_at",
    "type": "TIMESTAMP",
    "mode": "NULLABLE"
  },
  {
    "name": "created_at",
    "type": "TIMESTAMP",
    "mode": "NULLABLE"
  },
  {
    "name": "id",
    "type": "INTEGER",
    "mode": "NULLABLE"
  },
  {
    "name": "national_id",
    "type": "STRING",
    "mode": "NULLABLE",
    "policyTags": {
      "names": [
        "projects/sambla-data-staging-compliance/locations/europe-north1/taxonomies/7698000960465061299/policyTags/5051177413198927114"
      ]
    }
  },
  {
    "name": "updated_at",
    "type": "TIMESTAMP",
    "mode": "NULLABLE"
  },
  {
    "name": "ts",
    "type": "INTEGER",
    "mode": "NULLABLE"
  },
  {
    "name": "timestamp_ts",
    "type": "DATE",
    "mode": "NULLABLE"
  },
  {
    "name": "rn",
    "type": "INTEGER",
    "mode": "NULLABLE"
  },
  {
    "name": "source",
    "type": "STRING",
    "mode": "NULLABLE"
  },
  {
    "name": "xid",
    "type": "INTEGER",
    "mode": "NULLABLE"
  },
  {
    "name": "xoffset",
    "type": "INTEGER",
    "mode": "NULLABLE"
  }
]